README.md
setup.py
bin/ponctl
pypon/__init__.py
pypon/annotations_pb2.py
pypon/annotations_pb2_grpc.py
pypon/device_info.py
pypon/http_pb2.py
pypon/http_pb2_grpc.py
pypon/ind.py
pypon/openolt_pb2.py
pypon/openolt_pb2_grpc.py
pypon.egg-info/PKG-INFO
pypon.egg-info/SOURCES.txt
pypon.egg-info/dependency_links.txt
pypon.egg-info/requires.txt
pypon.egg-info/top_level.txt