Metadata-Version: 2.1
Name: pypon
Version: 0.0.0.8
Summary: White box PON OLT software
Home-page: https://github.com/shadansari
Author: Shad Ansari
Author-email: shad69@gmail.com
License: Apache License 2.0
Keywords: openolt pon whitebox
Platform: UNKNOWN
Classifier: Development Status :: 2 - Pre-Alpha
Classifier: Topic :: System :: Networking
Classifier: Programming Language :: Python
Classifier: License :: OSI Approved :: Apache Software License
